phoenix_sdk/__init__.py
phoenix_sdk/cluster/__init__.py
phoenix_sdk/cluster/auth.py
phoenix_sdk/cluster/awload.py
phoenix_sdk/cluster/cluster.py
phoenix_sdk/cluster/config.py
phoenix_sdk/cluster/model.py
phoenix_sdk/job/__init__.py
phoenix_sdk/job/ray_jobs.py
phoenix_sdk/templates/base-template.yaml
phoenix_sdk/utils/__init__.py
phoenix_sdk/utils/demos.py
phoenix_sdk/utils/generate_cert.py
phoenix_sdk/utils/generate_yaml.py
phoenix_sdk/utils/kube_api_helpers.py
phoenix_sdk/utils/pretty_print.py
phoenix_sdk-0.0.2.dist-info/LICENSE
phoenix_sdk-0.0.2.dist-info/METADATA
phoenix_sdk-0.0.2.dist-info/WHEEL
phoenix_sdk-0.0.2.dist-info/RECORD
