Metadata-Version: 2.1
Name: phoenix-sdk
Version: 0.0.2
Summary: Python SDK for codeflare client
Home-page: https://github.com/project-codeflare/codeflare-sdk
License: Apache-2.0
Keywords: codeflare,python,sdk,client,batch,scale
Author: Michael Clifford
Author-email: mcliffor@redhat.com
Requires-Python: >=3.9,<4.0
Classifier: License :: OSI Approved :: Apache Software License
Classifier: Programming Language :: Python :: 3
Classifier: Programming Language :: Python :: 3.9
Classifier: Programming Language :: Python :: 3.10
Classifier: Programming Language :: Python :: 3.11
Classifier: Programming Language :: Python :: 3.12
Requires-Dist: cryptography (==40.0.2)
Requires-Dist: executing (==1.2.0)
Requires-Dist: ipywidgets (==8.1.2)
Requires-Dist: kubernetes (>=25.3.0,<27)
Requires-Dist: openshift-client (==1.0.18)
Requires-Dist: pydantic (<2)
Requires-Dist: ray[data,default] (==2.23.0)
Requires-Dist: rich (>=12.5,<13.0)
Project-URL: Repository, https://github.com/project-codeflare/codeflare-sdk
